population.py
population-0.0.1.dist-info/LICENSE
population-0.0.1.dist-info/METADATA
population-0.0.1.dist-info/WHEEL
population-0.0.1.dist-info/top_level.txt
population-0.0.1.dist-info/RECORD
