Metadata-Version: 2.1
Name: population
Version: 0.0.1
Summary: A Python package to get population of countries.
Home-page: https://github.com/satyatomar/population.git
Author: satyapal singh tomar
Author-email: er.satyatomar@gmail.com
License: MIT
Platform: UNKNOWN
Classifier: License :: OSI Approved :: MIT License
Classifier: Programming Language :: Python :: 3
Classifier: Programming Language :: Python :: 3.7
